GitDownloader/__init__.py
GitDownloader/cli.py
GitDownloader/downloader.py
GitDownloader-1.0.19.dist-info/LICENSE
GitDownloader-1.0.19.dist-info/METADATA
GitDownloader-1.0.19.dist-info/WHEEL
GitDownloader-1.0.19.dist-info/entry_points.txt
GitDownloader-1.0.19.dist-info/top_level.txt
GitDownloader-1.0.19.dist-info/RECORD
