Metadata-Version: 2.1
Name: GitDownloader
Version: 1.0.19
Summary: A Python CLI tool for downloading files, directories, or entire repositories from GitHub, supporting recursive downloads for folders and the option to save files as a ZIP archive.
Home-page: https://github.com/PtPrashantTripathi/GitDownloader
Author: PtPrashantTripathi
Author-email: PtPrashantTripathi@outlook.com
Classifier: Programming Language :: Python :: 3
Classifier: License :: OSI Approved :: MIT License
Classifier: Operating System :: OS Independent
Requires-Python: >=3.7
License-File: LICENSE
Requires-Dist: requests
